mr_git
