Metadata-Version: 2.1
Name: mr-git
Version: 0.0.1.post1
Summary: Multi-Repositories Git tool
Home-page: https://github.com/pbauermeister/mr-git
Author: Pascal Bauermeister
Author-email: pascal.bauermeister@gmail.com
License: GNU General Public License v3 (GPLv3)
Project-URL: Bug Reports, https://github.com/pbauermeister/mr-git/issues
Project-URL: Source, https://github.com/pbauermeister/mr-git
Keywords: diagram-generator,development,tool
Classifier: Development Status :: 3 - Alpha
Classifier: Intended Audience :: Information Technology
Classifier: Intended Audience :: Developers
Classifier: Topic :: Software Development
Classifier: Topic :: Software Development :: Version Control
Classifier: License :: OSI Approved :: GNU General Public License v3 (GPLv3)
Classifier: Programming Language :: Python :: 3
Requires-Python: >=3.10, <4
Provides-Extra: dev
Provides-Extra: test
